{
    "res": 0,
    "data": [
        {
            "id": "8985",
            "category": "4",
            "display_category": 6,
            "item_id": "1159",
            "title": "天后的光环背面，是他在暗地中闪耀",
            "forward": "#王菲身边的男人们# 那些耀眼身影的背后，有张亚东不可磨灭的光彩。",
            "img_url": "http://image.wufazhuce.com/FozlYhB4qo7I6drURY1OXb_l0Yq-",
            "like_count": 85,
            "post_date": "2017-01-05 16:00:00",
            "last_update_date": "2017-01-03 18:13:03",
            "author": {
                "user_id": "7609430",
                "user_name": "白",
                "desc": "文艺生活周刊作者",
                "wb_name": "",
                "is_settled": "0",
                "settled_type": "0",
                "summary": "文艺生活周刊作者",
                "fans_total": "1",
                "web_url": "http://image.wufazhuce.com/FkmNWtaFy1GxpRkmAYotrWvhUbvh"
            },
            "video_url": "",
            "audio_url": "377118",
            "audio_platform": "1",
            "start_video": "",
            "volume": 0,
            "pic_info": "",
            "words_info": "",
            "subtitle": "只爱陌生人",
            "number": 0,
            "serial_id": 0,
            "serial_list": [],
            "movie_story_id": 0,
            "ad_id": 0,
            "ad_type": 0,
            "ad_pvurl": "",
            "ad_linkurl": "",
            "ad_makettime": "",
            "ad_closetime": "",
            "ad_share_cnt": "",
            "ad_pvurl_vendor": "",
            "content_id": "1159",
            "content_type": "4",
            "content_bgcolor": "#FFFFFF",
            "share_url": "http://h.xiami.com/one-share.html?id=377118",
            "share_info": {
                "url": "http://h.xiami.com/one-share.html?id=377118",
                "image": "http://image.wufazhuce.com/FozlYhB4qo7I6drURY1OXb_l0Yq-",
                "title": "「一个」音乐: 白 只爱陌生人",
                "content": "一个音乐制作人的故事，往往在幕后被人遗忘，堙没于歌手的动听，消失于明星的八卦，但他们的人生同样精彩。\r\n\r\n比如被王菲的传奇、窦唯的仙气、林夕黄伟文等的才华抢掉风头的张亚东，若以他为主角写一个剧本，那便是乐坛的另一段佳话。\r\n\r\n金牌制作人\r\n\r\n这个从小学音乐的男人，在人生经历上与窦唯确有相似。张亚东第一次与王菲合作，是带着点革命性质的《浮躁》，这张专辑抱着打破流行乐模式的野心。\r\n\r\n英伦摇滚和微妙民乐的搭配，加上王菲的个人哲学与灵气，让粉丝们对于究竟是窦唯影响王菲、还是王菲影响窦唯争得面红耳赤。殊不知，正是制作了一半歌曲的张亚东，把这张概念专辑把握得一气呵成。\r\n\r\n在此之前，张亚东参与制作了窦唯的《艳阳天》，因窦唯认识了王菲，之后便开启了二人的合作之路。前一阵王菲的演唱会发布会上，张亚东也以音乐总监的身份出席，足见二人多年的惺惺相惜。\r\n\r\n之后王菲的《只爱陌生人》、《寓言》，张亚东都参与了制作，《将爱》更是他全盘操刀。《将爱》的酷、《阳宝》的柔、《夜妆》的未来主义，汇在一起就是一张让王菲得了金曲奖最佳国语女演唱人的专辑。\r\n\r\n张亚东制作过的专辑还有窦唯的《山河水》、许巍的《在别处》、朴树的《生如夏花》、汪峰的《花火》；近年来还有田原、刘若英、莫文蔚等。说起来，合作者都是华语乐坛有思想有灵魂的歌者。\r\n\r\n会写歌的歌手\r\n\r\n张亚东算是半个幕后加上半个台前。他于98年推出个人专辑《Ya Tung》，这张专辑除了翻唱了一些他写给别人的歌，主打摇滚和实验电子，又一个与窦唯的巧合。第一首《Ah Sa Ba La》开头是人声采样，之后是温柔的吉他和缥缈的vocal，然后由一声炸裂的鼓突然变成让人想砸吉他的摇滚。\r\n\r\n而作为有个人风格的歌手，不难发现他为别人编曲的歌会带着一些他的味道。09年他发行了第二张专辑《潜流》请了一系列大牌来演绎，包括王菲、莫文蔚、坂本美雨等。整张专辑安安静静，酸性爵士的冷调中却有骚动的情绪，是他个人音乐审美的统合。\r\n\r\n除了这些专辑和为别人写的歌，他也为电影配乐，最著名的便是《蓝宇》。想必看过电影的人都不会忘记那弦乐扰人的蓝宇主旋律，在每一个欢快的情节里烙下黑洞。\r\n\r\n最爱的吉他手\r\n\r\n98年王菲在香港开“唱游大世界”演唱会，张亚东是吉他手，窦唯是鼓手，张亚东当时的妻子窦颖是和声，而王菲与窦唯当时已婚。\r\n\r\n可能再也找不出一场演唱会以double date的形式如此精彩耀眼，张亚东无疑是不可或缺的吉他手。\r\n\r\n除了吉他手，他还客串过钢琴手，他曾突然出现在莫文蔚的演唱会上为她钢琴伴奏。\r\n\r\n摄影师和未来的大导演\r\n \r\n除了以音乐作为表达自己的方式，张亚东还在影像上寻找思想出路。他不仅喜欢画画，还痴迷摄影，出过个人摄影集《初见即离别》，收录了旅行时拍摄的照片以及一些文字，记录了他的生活和思想。\r\n\r\n他的微博也几乎都是意识流摄影作品，寥寥几个词或是符号、黑白的照片。作为一个从小关上房门学音乐的人，摄影让他走出房门，在陌生的领域探索自己观察别人。\r\n\r\n除了这些个人照片，他还是杂志摄影师，风格如他的电子乐：冷、酷、骚。\r\n\r\n今年六月，他的电影《湖边密林》被提上了日程，并公布了很表现主义的海报。\r\n\r\n电影关于中年危机，是个让大家吃惊的主题。他本人却十分坦然，他说，中年是他现在最熟悉的状态，便想探讨褪去社会角色之后的归属感。\r\n\r\n在此之前他执导过一些短片，虽说是广告性质的命题作文，剧本也有些傻气：比如《11度青春之L.I》关于签订合约的情侣中，出轨的那个会被强制变成约定好的动物。情节虽简单，张亚东已显出了导演的控制和审美，那他的新片我们不妨拭目以待。\r\n\r\n\r\n或许因他才气，这些年与女明星绯闻不断，娱乐版倒也偏爱他。他却静静地活着，自谦般地说和窦唯比起来自己就是个俗人。但他毕竟也在做着不后悔的事，体验着自己想要的人生。"
            },
            "music_name": "只爱陌生人",
            "audio_author": "张亚东"
        },
        {
            "id": "9022",
            "category": "4",
            "display_category": 6,
            "item_id": "1164",
            "title": "离开王菲，其实他们还有一颗少女心",
            "forward": "#王菲身边的男人们# 别耻笑一个男人的少女心，说不定他就是王菲御用作词人。",
            "img_url": "http://image.wufazhuce.com/Fg6z6APJgqfjx58jBOjk1-GSSTQL",
            "like_count": 142,
            "post_date": "2017-01-05 12:00:00",
            "last_update_date": "2017-01-05 15:40:23",
            "author": {
                "user_id": "7538825",
                "user_name": "流忙忙",
                "desc": "黑长直萌妹脸、喜欢周杰伦五月天的金属宝宝。",
                "wb_name": "",
                "is_settled": "0",
                "settled_type": "0",
                "summary": "音乐编辑",
                "fans_total": "1",
                "web_url": "http://image.wufazhuce.com/FpmiakxmS_Jqia_RknGVLBA9gBKO"
            },
            "video_url": "",
            "audio_url": "3226300",
            "audio_platform": "1",
            "start_video": "",
            "volume": 0,
            "pic_info": "",
            "words_info": "",
            "subtitle": "相爱6年",
            "number": 0,
            "serial_id": 0,
            "serial_list": [],
            "movie_story_id": 0,
            "ad_id": 0,
            "ad_type": 0,
            "ad_pvurl": "",
            "ad_linkurl": "",
            "ad_makettime": "",
            "ad_closetime": "",
            "ad_share_cnt": "",
            "ad_pvurl_vendor": "",
            "content_id": "1164",
            "content_type": "4",
            "content_bgcolor": "#FFFFFF",
            "share_url": "http://h.xiami.com/one-share.html?id=3226300",
            "share_info": {
                "url": "http://h.xiami.com/one-share.html?id=3226300",
                "image": "http://image.wufazhuce.com/Fg6z6APJgqfjx58jBOjk1-GSSTQL",
                "title": "「一个」音乐: 流忙忙 相爱6年",
                "content": "这个时代再也没有少女偶像了。\r\n\r\n是吗？\r\n\r\n最早的青春美少女组合经历多次成员更换后，早就不知所踪；By2由曾经的未成年萌系少女，摇身一变成为了网红外围风，僵硬得连猪鼻子也做不出；挂着少女名号的“少女时代”更多的是因为她们的大长腿而成名……\r\n\r\n如今称得上少女偶像的，像SNH48、七朵组合，都是男粉丝居多，比起当年的全民偶像团体Twins、S.H.E，更是是差了好几个4 in love。而且再也没有像《恋爱大过天》、《女校男生》那样传唱度极高，能准确地击中你少女心的歌曲。\r\n\r\n如果说S.H.E的歌曲涵盖面更广，Twins早期的歌曲简直就是满满的少女心，而这些少女心往往都是来自于黄伟文和林夕，没错，就是那两个王菲的御用作词人，其实离开王菲，他们还有这样粉红色的一面。\r\n\r\n《明爱暗恋补习社》 \r\n词：黄伟文\r\n谁共我研讨 展开初恋的态度\r\nAB君谁又会 待我最好\r\n谈情可否当代数\r\n\r\n少女时期的你，很容易就喜欢上了一个人，只是因为A打球时的身影、因为B常穿的白衬衣，就喜欢上了他们，然后纠结着到底该选择谁。然而你并没有和A或者B说过一句话，唯一的的交集可能仅仅是你们的班级在同一个楼层。\r\n\r\n《女校男生》 \r\n词：黄伟文\r\n告诉我其实你\r\n原来曾为了他\r\n曾瞒着我离去\r\n做过普查\r\n\r\n关于喜欢的男生，你四处打听，几乎了解所有关于他的一切，生日、星座、血型、爱好甚至上学的路线。经常看星座书上的配对指数，然后暗自窃喜，而你做过最有勇气的事则是在离他50米处的身后，一路跟他回家，然后再回到反方向的自己家。\r\n\r\n《恋爱大过天》\r\n词：林夕\r\n学习大多 爱好太少 \r\n光阴一眨眼便跑掉\r\n为何他竟比功课更紧要\r\n\r\n上学时，父母老师们总是耳提面命告诉我们，学习最重要，千万不要谈恋爱。然而就是那样连写功课的时间都不够的时期，总是能滋长出最美好的恋情。小情侣们一起翘掉晚自习，只为了去校门口的小店吃一串炸年糕。\r\n\r\n《大浪漫主义》\r\n词：黄伟文\r\ntoday i dream\r\nyou hold me in your arms\r\nand you touch my head\r\nfeel like willling fall in love\r\n\r\n哪个少女不善怀春？那些个传阅言情小说、偷看偶像剧的年代，每个少女的脑内都有无数部以自己为女主角的几百集玛丽苏连续剧，幻想着有一天有一个少年会在大雨中冲进你的伞下。\r\n\r\n《我们的纪念册》\r\n词：林夕\r\n从此怎偷看校草\r\n才深深悔恨常常迟到\r\n他给我们支撑过每个清早\r\n\r\n现在想来也是好笑，永远都爬不起来的早自习的清晨，为了能刚好在那个时间点“偶遇”到校草，竟然也都起来了。每天都能见到他，竟是比考上好高中好大学更大的早起动力。\r\n\r\n《眼红红》\r\n词：林夕\r\n我最初脸红 现在双眼通红 \r\n再幼稚还是觉得恋爱如梦 \r\n我再不面红 但愿不再冲动 \r\n爱到入城大也分开 预计之中\r\n\r\n少女们总是抱着美好恋情的幻想，而很少想到任何东西都是一体两面的，恋爱带来甜蜜的同时，亦会带来苦涩和疼痛。于是在第一次分手时，像世界末日般哭到两眼通红。\r\n\r\n《朋友仔》\r\n词：林夕\r\n我也不想记起\r\n为当天衬衫似你　\r\n便心急妒忌\r\n其实我 都很小器\r\n\r\n少女们的友谊那么紧密又那么脆弱，亲密到上厕所都要一起去，脆弱到只因对方的衣服和自己相似就会心生妒忌。不过之后想起来，一起交换明星周边、偷看暗恋的人、因小事而吵架……那都是最美好的少女们的友谊啊。\r\n\r\n《风筝与风》\r\n词：林夕\r\n又那可一个 当风筝遇上风 　　\r\n即使快乐的痛 仍能乘着狂风 　　\r\n天空中爱得英勇 有你他就算哭 　　\r\n仍然流露着笑容 　\r\n\r\n少女从来都不是脆弱软弱的代名词，她们看似柔弱的外表下往往都有颗坚忍的金刚心。哪怕受委屈受伤害，依然能有勇气去追逐梦想和希望，哭完了亦不忘要以微笑示人。\r\n\r\n《下一站天后》\r\n词：黄伟文\r\n白日梦飞翔 永不太远太抽象\r\n最后变天后 变新娘都是理想\r\n在时代的广场 谁都总会有奖\r\n我没有歌迷有他景仰\r\n\r\n少女们总有很多梦想，想当大明星、想成为光鲜亮丽的白领、想做世界上最美的新娘。在那个恋爱大过天的时期，觉得能成为喜欢的人的新娘就是人生最大的梦想了。\r\n\r\n《饮歌》\r\n词：林夕\r\n曾遇上几多歌要天天唱六次 \r\n留下了几多首我喜欢到现时 \r\n到最后明白最好不应得一次 \r\n曾伴我 捱大过 应该会知\r\n\r\n少女时代的我们每天都有那么多的金曲可以传唱，手抄歌词本写满了好几本，又有几首歌真的唱出了你经历的少女时期，让你至今怀念呢？黄伟文和林夕写给Twins的这些歌一定包括在其中，前奏响起，那个甜蜜的少女时期扑面而来。\r\n\r\n《相爱6年》\r\n词：林夕\r\n从没心计 天真岁月已一齐\r\n幸福似季候交替\r\n你却永远企在旁像护堤\r\n\r\n光阴流逝，少女们也终将会变老，而少女心却不会随着季候交替而衰老，经历世事变迁后，依然可以像从前那样没有心计真诚地面对爱人和世界。\r\n\r\n《虚龄时代》\r\n词：黄伟文\r\n兜兜转转跟你都似一样\r\n可将青春封起储存那样\r\n为十八岁解冻\r\n曾新鲜的理想今天拆箱\r\n\r\n要知道，少女心这种东西啊，从来都跟年龄没有关系，从最初的《明爱暗恋补习社》，十几年后，黄伟文和伍乐城再度合体写了这首《虚龄时代》。阿Sa和阿娇各自经历了婚姻失败和事业低谷。但她们从未失去对未来的勇气，从未失去对爱情的向往，依旧有着少女才有的果敢和甜美笑容。\r\n\r\n唱出了我们所有少女心事的Twins，这才是少女偶像。\r\n\r\n究竟什么是少女心？少女心从来不简单意味着蝴蝶结、粉红色和蓬蓬裙，而是永远都对这个世界充满热爱和憧憬，永远都向往美好的东西，不管什么年纪都有勇气去做自己想做的事情，有梦想、有坚持、有原则，那才是“真”少女心。一如当年搜集喜欢人的情报时那么执着，而不管最后成功与否。\r\n\r\n这个时代也从来不缺少女偶像，满满少女心的你自己就是最棒的少女偶像啊。"
            },
            "music_name": "相爱6年",
            "audio_author": "Twins"
        },
        {
            "id": "9019",
            "category": "4",
            "display_category": 6,
            "item_id": "1166",
            "title": "王菲有过许多男人，却是某人没名分的妻子",
            "forward": "#王菲身边的男人们#“王菲对我的信任，是千金不变的。”",
            "img_url": "http://image.wufazhuce.com/Fqj5A3nGrDnmAoRUsZsigcFgI6OJ",
            "like_count": 181,
            "post_date": "2017-01-05 09:00:00",
            "last_update_date": "2017-01-03 18:14:12",
            "author": {
                "user_id": "7609810",
                "user_name": "超高能E姐",
                "desc": "资深记者杨蓓蓓创建，以学术的严谨看八卦，做娱乐圈最有深度及格调的现象学研究报告。ID：super_misse",
                "wb_name": "",
                "is_settled": "0",
                "settled_type": "0",
                "summary": "资深记者杨蓓蓓",
                "fans_total": "10",
                "web_url": "http://image.wufazhuce.com/FjcTdyyVe6pXcWmvZg2P9U2rKSrE"
            },
            "video_url": "",
            "audio_url": "147404",
            "audio_platform": "1",
            "start_video": "",
            "volume": 0,
            "pic_info": "",
            "words_info": "",
            "subtitle": "无奈那天",
            "number": 0,
            "serial_id": 0,
            "serial_list": [],
            "movie_story_id": 0,
            "ad_id": 0,
            "ad_type": 0,
            "ad_pvurl": "",
            "ad_linkurl": "",
            "ad_makettime": "",
            "ad_closetime": "",
            "ad_share_cnt": "",
            "ad_pvurl_vendor": "",
            "content_id": "1166",
            "content_type": "4",
            "content_bgcolor": "#FFFFFF",
            "share_url": "http://h.xiami.com/one-share.html?id=147404",
            "share_info": {
                "url": "http://h.xiami.com/one-share.html?id=147404",
                "image": "http://image.wufazhuce.com/Fqj5A3nGrDnmAoRUsZsigcFgI6OJ",
                "title": "「一个」音乐: 超高能E姐 无奈那天",
                "content": "泥萌还记得之前讨论的王菲“天价演唱会门票”吗！？山顶都要1800，这个价格可以买到别的歌手的前排！\r\n\r\n内场更是足足要7800，抵得过一台肾7~\r\n\r\n可是人家是天后耶，就算这个票价也只用了32秒也卖光了！\r\n\r\n买到票的网友还在微博上晒出了7800票价的伴手礼，手包+香水+定制项链，现在品牌商们只盯着赞助婚礼已经弱爆了好么？\r\n\r\n这大概就是传说中的“姐不在江湖，江湖上总有姐的传说”吧！\r\n\r\n就算王菲很久没有公开活动，但她日常中一点琐碎的细节都能冲上热点：\r\n\r\n最近被刷屏的新闻是和小谢像老夫老妻一样牵手遛弯；\r\n\r\n然后夫妻双双把家还，拿钥匙开门是真.老夫.老妻的既视感。\r\n\r\n然后大家的焦点转换到王菲的穿着，什么朴素接地气，什么走下“时髦”神坛，毕竟两个月以前去巴黎看CELINE大秀的时候是这样的：\r\n\r\nbut本组照片的核心不应该是拍拖嘛？谁下楼遛个弯还要穿成去时装周的style，更何况高冷如天后！\r\n\r\n自去年和小谢复合以来，二人被传结婚、怀孕的消息成了月经贴，王菲的情史也随之被一遍遍翻出来讨论。\r\n\r\n不过今天我们想聊的，是号称“与王菲是没有名分的夫妻”的一个人，熟悉王菲的人一定也知道，他是林夕。\r\n\r\nE姐科普\r\n\r\n林夕，原名梁伟文，香港著名词作家，专栏作家。\r\n\r\n为张国荣、梅艳芳、王菲、张学友、陈奕迅、张惠妹、张靓颖、周笔畅等两岸三地歌手的超过四千首音乐作品填词。\r\n\r\n代表作包括《怪你过分美丽》、《我》、《千千阙歌》、《红豆》、《至少还有你》、《十年》、《雪狼湖》、《北京欢迎你》等。\r\n\r\n林夕的原名叫梁伟文，林夕是个笔名，关于这个名字的来历，网上留言最多的是简体的“梦”自拆分而得。\r\n\r\n后来关于笔名的来历被以讹传讹，林夕只能自己出来解释：\r\n\r\n“最开始打算填词的时候，很喜欢林振强，所以选择了‘林’字，后来的确是看了简体版的《红楼梦》，见到林下面有个夕阳很漂亮，于是觉得不如就叫‘林夕’”。\r\n\r\n简言之，林是源自“林振强”，“夕”才是源自“梦”。可见林夕对于林振强的欣赏非同一般。\r\n\r\n▲林振强\r\n\r\n林夕曾提过林振强给夏韶声写的《空凳》说：“他有一首歌写空椅子，但其实是怀念他的父亲，写得真的很感人。”\r\n \r\n但林振强并非林夕走向词坛的领路人，让他走上填词道路的，是黄霑和卢国沾等更早的填词人，原因是他们包办了早期香港大部分电视剧的主题曲歌词。\r\n\r\n中学时候的林夕，听了电视剧《陆小凤》片尾曲《鲜花满月楼》后，觉得自己可以填出更好的词，就在洗澡时开始了最初的尝试，“现在有时想不到歌名我也会去洗澡，洗澡能让我想到比较好的歌名 ”。\r\n\r\n▲刘松仁版的古早《陆小凤》\r\n\r\n林夕在接受采访时阐释自己如何走上填词的道路时，将填词比作“游戏”：“我特别佩服他们能把一个特别复杂的电视剧（很多改编自金庸小说）浓缩在三言两语之中，那么精准地表达出来。从此，我就爱上这个游戏了。 ”\r\n\r\n不过二者相比，林夕还是更倾向于卢国沾，他曾在专栏里拿黄霑与卢国沾的几首作品比较，认为“如果对垒的话，卢国沾词作的优势是压倒性的。”\r\n \r\n1985年，林夕为钟镇涛所填《曾经》成为了他第一步发表的作品；1986年林夕正式入行，一边给乐队写歌词，一边在《词汇》上发表作品；\r\n\r\n▲早年以本名在《词汇》上发表作品的林夕\r\n\r\n上个星期三，林夕度过了他55岁的生日，也意味着作为一个音乐填词人，他在过去31年职业生涯里亲历了一个港乐的黄金年代。\r\n\r\n而他和王菲的搭档，或许就是这其中的一个缩影。\r\n\r\n▲1989年，还没有成“夕爷”的林夕，和还不是天后的王菲第一次合作，那时候王菲还叫王靖雯。\r\n\r\n移民香港后，跟随戴思聪学习了2年声乐的王菲，顺利签约新艺宝，并用“王靖雯”的名字发布了同名专辑。\r\n\r\n用“王靖雯”是因为这个名字听起来很“香港”，但后来王菲又义无反顾的改回了“王菲”。\r\n\r\n《王靖雯》这张专辑一共收录了10首歌，其中来自词作林夕的是《无奈那天》。\r\n          \r\n林夕后来透露，第一次给王菲写词的时候林夕心理是有疑问的：“听说这个女生是从北京来的，唱粤语歌行不行啊？”\r\n\r\n王菲的声线给林夕的答复是肯定的，以至于在之后王菲的大部分专辑中，都可以看到林夕操刀的作品。包括《红豆》，《开到荼蘼》，《人间》，《给自己的情书》，《约定》等经典。\r\n\r\n长时间的合作，彼此的认知不断深入，自然加深了二人的默契，音乐也就融入了彼此生活中：\r\n\r\n比如林夕的词意境唯美，但不免有些生涩的部分。林夕说，有些歌词就连唱了歌的王菲也没弄懂，但她的好处是从来不乱问，所以彼此才能合作十多年。\r\n\r\n比如林夕和王菲都对佛教有所执念，王菲皈依佛门不用说，林夕也经常在歌词和散文里化用佛教用语。所以就有了《彼岸花》、《阿修罗》、《情诫》、《色诫》等。\r\n\r\n林夕曾说：“我发现她信佛以后，我就更放心把多一些那些想法，放在她的歌词里面。”\r\n\r\n比如1997年，王菲生下窦靖童之后，《人间》这首歌词是林夕为童童所写。\r\n\r\n但愿你的眼睛 只看得到笑容\r\n但愿你流下每一滴泪都让人感动\r\n但愿你以后每一个梦不会一场空\r\n——《人间》\r\n\r\n再比如到了1998年，王菲与窦唯的感情破裂，恰巧林夕也处于失恋期间，他就写了《暗涌》、《百年孤寂》等作品，以此鼓励王菲、也鼓励自己感情要“拿得起放得下”。\r\n\r\n背影是真的 人是假的 没什么执着\r\n一百年前 你不是你 我不是我\r\n悲哀是真的 泪是假的 本来没因果\r\n一百年后 没有你 也没有我”\r\n——《百年孤寂》\r\n\r\n生下窦靖童之后，王菲从新艺宝转到百代唱片公司，林夕也大量的进行一曲两词——国语和粤语歌相同的曲但是完全不同的歌词意境。\r\n\r\n而此前填词界的惯例是，只将文字修改一下，适合另一种语言的发音即可，意思、结构不做更改。\r\n\r\n王菲产后复出的第一张专辑《王菲（97）》，她加入百代有个条件就是不再发行粤语专辑。\r\n\r\n林夕却为王菲写了很多“一曲双词”，如粤语《偿还》国语《红豆》，粤语《情诫》国语《色诫》，粤语《给自己的情书》国语《笑忘书》等。\r\n\r\n2003年，王菲发行最后一张专辑《将爱》，据传为林夕布置了一次“命题作文”，就是王菲定歌名，林夕来填词，这首歌就是《花事了》作为对四年前《开到荼蘼》的一个延续。\r\n\r\n“开到荼蘼花事了”原本就是宋诗《春暮游小园》中的一句，意思是到了最高兴的时候却也是该结束的时候，表示快乐的时间短暂。\r\n\r\n《开到荼蘼》对林夕也意义非凡，曾经有采访让他在每个年代选一首对自己有影响的歌。他说，“七十年代是《家变》，八十年代是《忘记他是她》，九十年代……《开到荼蘼》，这是我自己的。”\r\n\r\n不少港乐爱好者将这两首歌视为二人之间感情的一种连结，《花事了》唱完后，王菲随减少露面，经历转移到家庭，逐渐进入半隐退状态。\r\n\r\n现在王菲依然把大把精力投注在李老师身上。\r\n\r\n林夕与王菲的成长轨迹几乎是同时的，相逢于微时，彼此成就走向各自事业的高峰。\r\n\r\n当然，也不是谁离不开谁，或许只是一种因缘，成就了更好的彼此。\r\n\r\n正如林夕所说：“王菲的气质，性格是我偏好的类型。王菲对我的信任，也是千金不变的。”\r\n\r\n林夕与王菲相识时，林夕虽然已入行几年，也远未达到在词坛呼风唤雨的程度；王菲更是刚出道。\r\n\r\n但张国荣不同，林夕年第一次为哥哥写的歌是1986年的《妄想》。那时林夕初出茅庐，但哥哥已经是天皇巨星。\r\n\r\n1986年，经过倪震的介绍，林夕与哥哥相识。但是这次相识并不是晚辈的林夕去拜访大明星张国荣，而是张国荣亲自来林夕家里。\r\n\r\n林夕还在《天天向上》中回忆过这个初次相见的场景：“一部红色的跑车，敞蓬的，他一个人开，fung的一声就停在楼下。这个镜头，我这辈子都记得，太帅了。”\r\n\r\n感觉夕爷当年也是小粉红的迷弟啊！\r\n\r\n但是哥哥进林夕家第一句话却是“你的屋子这么小，怎么住啊”，林夕还默默的怨恨了一下，心想“为什么你要提醒我呢，房子真的是很小，很难放得下东西，可能那个时候我还没有那么多东西。 ”\r\n\r\n后来林夕去张国荣家回访，看到位于浅水湾宝华大厦的复式豪宅，觉得特别大，甚至林夕看楼盘的习惯，也是从去哥哥家的这个经历开始的。\r\n\r\n因为林夕除了填词之外，从1988年开始投资房地产——这才是林夕最重要的收入来源，有“地产小王子”的花名。\r\n\r\n用上千万的投资收入养着填词的爱好，可能也是林夕对填词不会腻烦，一直保持热爱的一个原因吧。\r\n\r\n不过，谈起和哥哥的第一次合作，林夕对自己的作品并不满意。\r\n\r\n他曾说，“现在回来听（《妄想》），不如不要听，因为填得实在太差了，但那时我很开心，很尽力，当时我实在未成熟”\r\n\r\n但是哥哥依然对林夕依然抱以很大的信任，1987年找林夕写了《无需要太多》，这首歌在十大劲歌金曲中获了奖。\r\n\r\n不过二人的后续合作没有进行太多，因为不久后张国荣选择了退出歌坛。\r\n\r\n1990年，在哥哥的“告别歌坛演唱会”上，林夕哭的最伤心的就是听到《明星》这首歌。\r\n\r\n看完演唱会之后，倪震开车接林夕离开，倪震一边劝林夕别哭了，一边在车上继续放《明星》，惹的林夕抱怨倪震在“捉弄”自己。\r\n\r\n不过好在1995年，张国荣又重回乐坛，在回归之作《宠爱》中，林夕奉献了总共十首歌中的三首词作，其中包括经典的《追》。\r\n\r\n在张国荣后来的所有作品里，几乎都有林夕的词作。\r\n\r\n1991年，张国荣第21张专辑《红》。有种说法是，张国荣中后期的经典作品，大多数来自林夕的填词，比如《追》，比如《春夏秋冬》，比如《最冷一天》。\r\n\r\n其中《红》这张专辑中的《怪你过分美丽》，在荣迷心里有至高无上的地位。\r\n\r\n哥哥和舒淇的MV，尺度不小，但女神真的好美~（舒淇后半段才出场）\r\n\r\n不过林夕写歌时并没有意识到这首歌的重要性，当时听到了旋律，“过分美丽”几个字就跳进了他的脑海里。\r\n\r\n而写这首歌的原因，只因林夕见别人都称赞张国荣“靓”，所以想写个更“厉害的”。\r\n\r\n他说：“黄霑赞张国荣‘眉目如画’，倪匡同样赞他‘眉目如画’，两大高人都赞他‘眉目如画’，我怎么就不能写一个更加厉害的《怪你过分美丽》？ ”\r\n\r\n直到1997年才在演唱会上承认与唐生的恋情，后期作品也有了更多大胆的突破\r\n\r\n2000年热情演唱会上，张国荣请来了法国鬼才设计师让.保罗.高缇耶为他量身打造了雌雄同体的造型。\r\n\r\n可惜这次的造型遭到一些媒体“乱写”，最主要的评语就是“妖”。\r\n\r\n面对这些绯言绯语，让.保罗.高缇耶一怒之下扬言不再给亚洲歌手做演唱会造型，直到十多年之后的李宇春，当然这些都是后话。\r\n\r\n面对媒体的乱写，张国荣曾在林夕面前破口大骂，林夕安慰并奉劝哥哥，找一家中肯的媒体接受采访，争取让更多的人理解自己。\r\n\r\n《怪你过分美丽》之后，另一首经典《我》也在林夕笔下诞生了。\r\n\r\n林夕曾毫不客气的说：“我这辈子最光荣的一件事是帮张国荣写了一首歌，名字叫《我》，有广东版，有国语版，国语版还可以传到内地呢。”\r\n\r\n关于这首歌，林夕还原过哥哥和他之间的一场对话：\r\n\r\n“喂，你有没有看过一出戏，叫作《假凤虚凰》没有？”\r\n我说看过，怎么？\r\n“意思就是‘I am what I am’”。\r\n我说“这样啊，好，你等我来啦”\r\n“你知不知道写什么啊？”\r\n“哦，你想写gay嘛！知道你威风，很骄傲的！行，像你一样骄傲！”\r\n\r\n《我》问世三年之后，哥哥纵身一跃，结束了一个时代。\r\n\r\n消息传来时，罗大佑正在接受一个访问，记者问想说什么，罗大佑说：“我最担心林夕，他是张国荣的好朋友，我怕他感情上接受不了。”\r\n\r\n罗大佑和林夕曾在音乐工厂共事，林夕曾表示自己有机会跟台湾乐坛交流并开展写国语歌生涯，罗大佑的帮助很大。\r\n\r\n1995年以后，林夕在香港乐坛的地位日益稳固，和wyman一道成为词坛双霸，慢慢变成“夕爷”。\r\n\r\n歪门和几分娇羞的夕爷，2011Cash金帆音乐奖「最佳填词人」由二人共同获得\r\n\r\n只是林夕终成夕爷，哥哥与林夕的合作却已是绝唱。\r\n\r\n某年哥哥冥诞，林夕写下了这样的话：“散聚有时，风光无限。感激完美主义者哥哥为我们吹遍千娇百媚的风潮。有空气就会有风，风会继续吹。”\r\n\r\n另一方面，王菲的复出，让我们有机会看到她与林夕的再度携手。\r\n\r\n《匆匆那年》里“如果再见不能红着眼，是否还能红着脸”，空灵的唱腔和缥缈的歌词，不知道会不会唤起二人多年前合作的回忆。\r\n\r\n2010年，王菲复出后在香港的演唱会，林夕不仅前来捧场，还去后台留下了这张探班的合影。\r\n\r\n今年王菲在上海又要开个唱了，虽然时不时就出个演唱会炒出天价票的新闻，但还是要期待一下，夕爷会不会前来。\r\n\r\n毕竟林夕谈王菲，酸起来也是肉麻到不要不要的，比如：\r\n\r\n“王菲不唱了，我如失半臂”\r\n“王菲是国宝，不知道几十年能不能出一个”\r\n““王菲是我的皮”\r\n“王菲是我的大女儿”\r\n“我和王菲是无名分的夫妻”\r\n\r\n酸归酸，倒也希望两位拍档能再多奉献一些佳作；\r\n\r\n林夕说，他和王菲“谁成就了谁根本不重要，因为这就是一场因缘。”\r\n\r\n其实他们与歌迷又何尝不是如此，音乐没有对错之分，他们的歌会一首一首唱下去，林夕的词会一句一句写下去，我们也会一遍一遍听下去。\r\n\r\n▲一张林夕，雷德颂，王菲，黎明，张学友，陈洁仪的旧照\r\n\r\n今天的这期就到这里，有句话叫“林夕引入门，皈依黄伟文”，一代鬼才黄伟文又有哪些故事呢？留待下回分解。"
            },
            "music_name": "无奈那天",
            "audio_author": "王菲"
        },
        {
            "id": "9205",
            "category": "4",
            "display_category": 6,
            "item_id": "1209",
            "title": "在这样的霾里我们人人都是蒸汽朋克",
            "forward": "只要天天雾霾天，我出门就是朋克，不惧生死，我行我素。",
            "img_url": "http://image.wufazhuce.com/Flw6kUfrnaBHomzrzJuBCiV7FuPf",
            "like_count": 62,
            "post_date": "2017-01-05 08:00:00",
            "last_update_date": "2017-01-05 11:02:01",
            "author": {
                "user_id": "7646936",
                "user_name": "克洛明",
                "desc": "正在找工作的社会闲散人员，微信ID：azaz1237",
                "wb_name": "",
                "is_settled": "0",
                "settled_type": "0",
                "summary": "正在找工作的社会闲散人员",
                "fans_total": "2",
                "web_url": "http://image.wufazhuce.com/FuLlEpIW-WVxwVQeYU8Kx4LTRh6o"
            },
            "video_url": "",
            "audio_url": "1769310575",
            "audio_platform": "1",
            "start_video": "",
            "volume": 0,
            "pic_info": "",
            "words_info": "",
            "subtitle": "Until the Day You Die",
            "number": 0,
            "serial_id": 0,
            "serial_list": [],
            "movie_story_id": 0,
            "ad_id": 0,
            "ad_type": 0,
            "ad_pvurl": "",
            "ad_linkurl": "",
            "ad_makettime": "",
            "ad_closetime": "",
            "ad_share_cnt": "",
            "ad_pvurl_vendor": "",
            "content_id": "1209",
            "content_type": "4",
            "content_bgcolor": "#FFFFFF",
            "share_url": "http://h.xiami.com/one-share.html?id=1769310575",
            "share_info": {
                "url": "http://h.xiami.com/one-share.html?id=1769310575",
                "image": "http://image.wufazhuce.com/Flw6kUfrnaBHomzrzJuBCiV7FuPf",
                "title": "「一个」音乐: 克洛明 Until the Day You Die",
                "content": "上一次雾霾的时候，我们的大妈上演了这么一场鬼片。\r\n\r\n我们身处的自然界是个巨大的蒸汽机，在这样的大蒸笼里，大妈们面不改色心不跳完成一套套优美的动作（猜测如此，反正我也看不见）。\r\n\r\n然而，时代的进步让我们有更好的措施成为雾霾战士。比如说，在这样的天赐良机下成为一个蒸汽朋克。\r\n\r\n对啊，酷的人戴什么口罩，酷的人都戴防毒面罩，一起上演一场蒸汽朋克的 cosplay。\r\n\r\n就像老人们将广场舞的精神发挥到极致，哈雷路亚，雾霾战士！\r\n\r\n\r\n年轻人也不甘落后，跑长跑、拍结婚照，没有什么能够阻挡。\r\n\r\n\r\n别光喊口号了。蒸汽朋克，从你我做起。\r\n\r\n只要天天雾霾天，我出门就是朋克，不惧生死，我行我素。\r\n\r\n\r\n前几天朋友圈里被北京的朋友们拍的景色刷屏了，结果今天好像被北风一吹天又蓝得跟魔幻现实似的，所以说，像那样的天气我们要珍惜，不是谁都可以随时就做蒸汽朋克的。"
            },
            "music_name": "Until the Day You Die",
            "audio_author": "Abney Park"
        },
        {
            "id": "9164",
            "category": "4",
            "display_category": 6,
            "item_id": "1203",
            "title": "唯颜值与才华匹配者，才是一辈子的春药",
            "forward": "人间值得歌颂因为你不想看懂。",
            "img_url": "http://image.wufazhuce.com/FiiEJk7bOXtvVCIPvmch_gi-M3Vr",
            "like_count": 509,
            "post_date": "2017-01-05 06:00:00",
            "last_update_date": "2017-01-03 19:06:09",
            "author": {
                "user_id": "7642770",
                "user_name": "江灿",
                "desc": "微信公众号：江灿（ID：dacan94）\r\n微博：URNOT江灿",
                "wb_name": "",
                "is_settled": "0",
                "settled_type": "0",
                "summary": "姬圈国家级撸串运动员",
                "fans_total": "13",
                "web_url": "http://image.wufazhuce.com/Frz9-FuFnriH1nUfsqacI3uNf_VB"
            },
            "video_url": "",
            "audio_url": "1772226282",
            "audio_platform": "1",
            "start_video": "",
            "volume": 0,
            "pic_info": "",
            "words_info": "",
            "subtitle": "Blue Flamingo",
            "number": 0,
            "serial_id": 0,
            "serial_list": [],
            "movie_story_id": 0,
            "ad_id": 0,
            "ad_type": 0,
            "ad_pvurl": "",
            "ad_linkurl": "",
            "ad_makettime": "",
            "ad_closetime": "",
            "ad_share_cnt": "",
            "ad_pvurl_vendor": "",
            "content_id": "1203",
            "content_type": "4",
            "content_bgcolor": "#FFFFFF",
            "share_url": "http://h.xiami.com/one-share.html?id=1772226282",
            "share_info": {
                "url": "http://h.xiami.com/one-share.html?id=1772226282",
                "image": "http://image.wufazhuce.com/FiiEJk7bOXtvVCIPvmch_gi-M3Vr",
                "title": "「一个」音乐: 江灿 Blue Flamingo",
                "content": "窦靖童身上有王菲的潇洒自在，看到童童，就会让我想起《重庆森林》里的王菲，浪漫率性，羞涩得惹人喜爱。\r\n\r\n窦靖童就像一只春天的小鹿横冲直撞般的闯进你心里。\r\n\r\n我一个89年的朋友老是说自己老了，就像是菲茨杰拉德说的那样：“自我”像一支箭一样，不停地从虚无射向虚无。\r\n\r\n今年，她去看了童童的表演，她在微信里告诉说看到窦靖童感觉自己像是陷入了一场热恋，大呼，没救了！太好看了！又酷又奶！\r\n\r\n前几天王菲《幻乐一场》的演唱会上，窦靖童担任伴唱，几处与王菲的甜蜜互动更是让迷妹们百看不厌。\r\n\r\n果真，长得好看，才是一辈子的春药。\r\n\r\n1.令人惊艳的横空出世\r\n\r\n我想没几个人不知道窦靖童吧，窦靖童作为王菲和窦唯的女儿，她在世人眼中，完全是神雕侠侣的后代。\r\n\r\n从窦靖童1997年1月3日出生的那一瞬间，作为“窦唯王菲结合体”，她的一生都注定是焦点。\r\n\r\n毕竟，“整个华语乐坛都在等她长大啊”。\r\n\r\n2011年，对音乐充满热爱的窦靖童，组建了自己的乐队并担任主唱。\r\n\r\n2012年12月，15岁的窦靖童以一首《With You》拉开了她展示其音乐才华的序幕。\r\n这让所有人都对这个从出生开始就备受瞩目的孩子更加期待。\r\n\r\n2014年她用一首单曲《My Days》彻底地刷爆了社交网络，就像一根火柴划过所有人的心脏动脉。\r\n\r\n童童的声音里有王菲的空灵，也拥有窦唯一般的桀骜和深沉。\r\n\r\n以技惊四座的姿态出场，让所有人都抬起头来赞叹到这个让“整个华语乐坛都在等着她长大”的孩子已经锋芒初露了。\r\n\r\n2.成熟独立，特立独行\r\n\r\n就在那首《My Days》刷爆社交网络的那一年，窦靖童剪去长发，以一头利落张扬的短发示人，并在社交网络上展示她的纹身，以及和女孩子的亲密合照。\r\n\r\n这让很多人在她身上贴上了叛逆的标签。其实，她并不是叛逆，她只是没有被束缚过，她只是一个在父母放养下成长起来的孩子，有着和年龄不符合的独立和成熟。\r\n\r\n回溯窦靖童的成长经历，她在14岁那年就和几个同学一起组了个乐队，开始了对音乐的探索之路。\r\n\r\n一年后，对自己人生充满主见的窦靖童拒绝了李亚鹏为她苦等到的入读重点中学的机会，也放弃了在中国的学业，去美国学习音乐。\r\n\r\n在一次采访中，窦靖童讲起小时候奶奶给她唱的京剧和儿歌，除此之外，她几乎没有在媒体面前主动提到过家人。\r\n\r\n她也表示自己很少听取别人的意见。\r\n\r\n“如果我真的没有把握，才会去征求朋友的意见。但如果不是那种对错分明的事情，我就自己拿主意。”\r\n\r\n在绝大多数90后连大学选专业都不得不屈从父母的时候，窦靖童已经完全掌控了自己的人生走向。\r\n\r\n后来，窦靖童从美国那所音乐学校离开后，她更加确信自己要成为一名歌手，就像她的父母那样。\r\n\r\n窦靖童也和大多数星二代一样都面临同样的尴尬，相比他们的作品，人们更关注他们的私生活。\r\n\r\n大多数媒体在采访中很爱故意提问窦靖童关于谢霆锋，大多数人也喜欢以戏谑的方式看待窦靖童和窦唯、李亚鹏、谢霆锋的关系。\r\n\r\n窦靖童成熟的看待母亲与继父李亚鹏的婚姻关系，在王菲、李亚鹏离婚后发了这样一条微博“The pain is real, but life goes on”\r\n\r\n关于她和谢霆锋，在最近的新闻里拍两人见面后热情拥抱，还在一起抽烟聊天的画面。\r\n\r\n3.张扬而不张狂，她只是在做自己\r\n\r\n因为父母都是非常顶尖的音乐人，窦靖童会受到超出常人的关注，也会受到超出常人的质疑。\r\n\r\n甚至，有人直言“窦靖童的音乐算是中规中矩，有受norah jones，johnmayer以及一些现代爵士的影响。但说实话，这种音乐其实在欧美挺普通的。受众人群在国内又不是特别多，如果没有他爹妈的影响力这张专辑在国内肯定无人问津。”\r\n\r\n面对质疑，她不曾却步，她自始自终专注于做自己的音乐，没有辜负自己的期待也没有妥协于世俗。\r\n\r\n迄今为止，窦靖童有条不絮的发了14首单曲，在今年4月，窦靖童发行了自己的首张原创专辑《Stone Caf&eacute;》，这些都是只属于她自己的音乐。\r\n\r\n当所有人都以为窦靖童作为“窦唯王菲结合体”会给华语音乐带来一波流行狂潮，成为另一个王菲或窦唯时。\r\n\r\n她却给长河来了个猝不及防的急转弯，偏离了以往的旧路，劈开了一条全新的河道，浩浩荡荡，奔流不息。\r\n\r\n如果你认真去听窦靖童的歌，从《my days》到《Lola》，你就会发现她的歌里有着很干净清爽的暧昧感，迷幻利落的性感。窦靖童创造出属于她自己的音乐世界。\r\n\r\n用一句通俗的话来讲就是，摇滚的窦唯和流行的王菲生出了一个爵士女窦靖童。\r\n\r\n窦靖童的音乐只表达她自己的想法和创意，不是当下华语音乐流行什么，就跟着写什么，唱什么。\r\n\r\n窦靖童更不会像大多选秀歌手那样高呼“音乐是毕生梦想。”什么砸锅卖铁也要坚持下去。\r\n\r\n对于窦靖童来说，音乐不是她谋生的手段，她也没觉得她做一辈子的歌手。\r\n但她明确表示在她的生活中“音乐，肯定是一辈子少不了了。”\r\n\r\n她做音乐不是因为玩音乐很酷很帅，只是因为自己发自内心的热爱音乐。\r\n\r\n窦靖童为什么能够张扬而不张狂的做自己呢？\r\n\r\n我想这都跟她的经历有关，她在北京、香港、日本、美国都上过学，在一部关于窦靖童的纪录片中，她说：“行走在外的时候，我不会去想这个地方是不是我家。没有哪一个地方是让我觉得最舒服的。这是我无法表达清楚的东西。每当我去到一个新地方或者认识新的人，他们都能给你一种特别的感觉，这种感觉只属于那个人或者那个地方，我无法描述。”\r\n\r\n这些经历融都进她的血液里，潜移默化地影响到她。\r\n\r\n突然想到了著名企业家，探险运动家王石先生拍过的一个广告。\r\n\r\n王石在广告里说“当你仰视着我，你看到的是王石，还是一个符号。这个符号充斥着被世俗反复夸耀的成功，却跟我毫无关系。真正靠近自己，你明白那些融进你生命里的，不是万科，不是珠穆朗玛，或者乞力马扎罗，而是走向它们和告别他们时，留下的脚印。正是这样的经历而非名字，决定了这个世界只有一个独一无二的我，和一个独一无二的你。用你的经历定义自己。”\r\n\r\n窦靖童只是窦靖童，她用她的经历定义了她自己。\r\n\r\n4.始于颜值，陷于才华\r\n\r\n写到这里，突然想起了想起了刷爆微博的那句话“喜欢一个人，始于颜值，陷于才华，忠于人品。”\r\n\r\n也许你最初喜欢窦靖童是因为她的才情吸引，迷醉于她特立独行的个性和音乐。\r\n或者是因为她的颜值，因为她在舞台上举手投足间的随性魅力。\r\n\r\n但是，随着你对她的深入了解，你为她彻底沦陷，因为她一直走自己的路，只做她自己。\r\n\r\n她就像玩一样认真的做着自己热爱的音乐。\r\n\r\n看似叛逆，不羁的外表之下却有着超越年龄的成熟和诚恳。\r\n\r\n很喜欢童童羞涩微笑的样子，嘴角轻微上扬的时候，流露出些许不羁孤傲。\r\n\r\n面对误解，窦靖童说:“如果你想了解我，就去听我的音乐。”\r\n\r\n\r\n作者介绍：\r\n江灿\r\n姬圈国家级撸串运动员\r\n公众号：江灿（ID：dacan94）"
            },
            "music_name": "Blue Flamingo",
            "audio_author": "窦靖童"
        },
        {
            "id": "9097",
            "category": "4",
            "display_category": 6,
            "item_id": "1187",
            "title": "陈升与徒弟金城武、刘若英、任贤齐的故事",
            "forward": "#那些一开口就不一样的男声#阿武，你还记得我吗，我是你师傅。",
            "img_url": "http://image.wufazhuce.com/FiPFK9qGiIwWzUBJ7d1Vjp6bQIFQ",
            "like_count": 434,
            "post_date": "2017-01-04 21:00:00",
            "last_update_date": "2017-01-03 23:07:50",
            "author": {
                "user_id": "0",
                "user_name": "国士岐黄",
                "web_url": "",
                "summary": "",
                "desc": "",
                "is_settled": "",
                "settled_type": "",
                "fans_total": "",
                "wb_name": ""
            },
            "video_url": "",
            "audio_url": "5384",
            "audio_platform": "1",
            "start_video": "",
            "volume": 0,
            "pic_info": "",
            "words_info": "",
            "subtitle": "把悲伤留给自己",
            "number": 0,
            "serial_id": 0,
            "serial_list": [],
            "movie_story_id": 0,
            "ad_id": 0,
            "ad_type": 0,
            "ad_pvurl": "",
            "ad_linkurl": "",
            "ad_makettime": "",
            "ad_closetime": "",
            "ad_share_cnt": "",
            "ad_pvurl_vendor": "",
            "content_id": "1187",
            "content_type": "4",
            "content_bgcolor": "#FFFFFF",
            "share_url": "http://h.xiami.com/one-share.html?id=5384",
            "share_info": {
                "url": "http://h.xiami.com/one-share.html?id=5384",
                "image": "http://image.wufazhuce.com/FiPFK9qGiIwWzUBJ7d1Vjp6bQIFQ",
                "title": "「一个」音乐: 国士岐黄 把悲伤留给自己",
                "content": "二十岁的眼泪——金城武\r\n\r\n《我是歌手2》半决赛，张宇演唱了陈升这首《二十岁的眼泪》。本来沧桑的嗓子，再加上喉咙生病打了封闭针，嘶哑的歌声，如酒倒鼻喉，芥末搽面，呛然泪下，网上多人说，看哭。\r\n\r\n《二十岁的眼泪》是年近四十的陈升，写给徒弟金城武的歌，给他20岁的生日礼物。\r\n\r\n这首歌，不经历社会打磨，无法完全体会。这歌是四十岁的过来人，对20岁后生敞开心。家伙20岁了，就应该开始成熟，担当，像个男人一样，不要有了挫折就掉泪。认真工作的同时，趁年轻多交朋友，体验不同的生活。因为，其他都可以再来，只有年轻，时光不再。\r\n\r\n20的金城武没能明白师傅的絮叨，无法理解让他放下纸笔，打开门窗，和朋友一起去游山玩水。因为日籍和家庭的原因，本来性格就很闷的他，把自己关在房间里，不停的谱曲，他有天赋，但是，音乐需要洞悉社会人心，接触大自然，尤其是陈升的路子，更是如此。 \r\n\r\n金城武的沉闷和内敛，与陈升产生了极大的冲突，陈升怒骂他的音乐是稻草堆砌的音符。 \r\n\r\n即使如此，陈升在金城武身上也付出了很多心血，帮他前后出了8张专辑，但销量非常惨，张张赔钱。\r\n\r\n金城武摔了吉他，与陈升闹掰，发誓不再碰音乐，全身投入影视拍摄中去。努力的人总会成功的，何况他还长得这么帅，他红了。 \r\n\r\n多年以后，陈升在节目中说，有次我也到了北京，我站在远远的人群外，给金城武写了封信：阿武，你还记得我吗，我是你师傅。但至今没收到他的回信。\r\n\r\n是否你走过了我身边，恍恍惚惚一瞬间——刘若英\r\n\r\n你问我怕什么 \r\n怕不能遇见你 \r\n是否你走过了我身边 \r\n恍恍惚惚一瞬间 \r\n——陈升《牡丹亭外》\r\n\r\n他的另一个徒弟刘若英，和金城武相反，她想一辈子黏在师傅身边。 \r\n\r\n然而他却主动推开了她，你是自由的，是时候离开了，他主动停止了已经走红的刘若英的合约。 \r\n\r\n2011年，苦恋陈升16年的奶茶终于找到自己的‘司机老王’。（陈升曾说：这个世界男人都死光了吗，随便一个人，随便一个哪怕是司机老王，来照顾她。\r\n\r\n面对泪眼婆娑期待的她，他说再给你唱最一首歌吧，唱完这首你不要再来找我，我有我的事，你去打拼你的事，你回北京去，我们不要再联系；\r\n\r\n吉他声响起，他闭上眼，用台语唱：\r\n\r\n送你到火车头 越头就做你走 情像断线风吹 双人放手就来自由飞自由飞 阮还有几句话 想要对你解释 看是藏底心肝底较实在 阮嘛有每天等 只惊等来的是绝望 想来想去 抹冻辜负著青春梦 青春梦 咱两人相欠债 你欠阮有较多 归去看破来切切 较实在。 ——《纯情青春梦》\r\n\r\n据说，这期节目播出后，观看了节目的港台女人全部泪雨滂沱。\r\n\r\n亦师亦友——任贤齐\r\n\r\n任贤齐是搞体育的，被一家小唱片公司忽悠，签约去做音乐，加入不到半年，公司就倒闭了。任贤齐就这样与桌椅板凳一起打包卖给了滚石唱片；\r\n\r\n任贤齐分配带他的人是小虫。小虫是台湾音乐三大教父之一，与罗大佑、李宗盛齐名；小虫同时是台湾四大幕后制作人之一，可以想象他是多么的炙手可热。当时的小虫压根没时间来管任贤齐，任贤齐像野草一样在滚石熬了三年。\r\n\r\n这三年，任贤齐多亏陈升，带着做活动，给他一些曝光的机会，自己的活动不落下他，金城武，刘若英的歌会，也常带上他，否则很难坚持下来。任贤齐从陈升身上学到的是平常心，以及对音乐严苛的态度。\r\n\r\n一直到三年后，小虫写了首《心太软》，找不到适合的人来唱，才注意废闲三年的跟他的任贤齐，身上悲剧色彩和歌词很搭，然后交给他来唱，一炮而红。\r\n\r\n当然，任贤齐能成功，一是小虫后来的鼎立支持，二是从陈升身上所学的东西。不过，我个人强调一点，他成功，主要还是他自己毅力，坚持，以及努力；纵观刘若英、金城武、任贤齐之所以成功，最主要是努力和加持，在这其他任何行业也一样。个人看法，可过。\r\n\r\nso，今天任贤齐开了自己的公司，签了不少人，音乐教父罗大佑已经签入任贤齐旗下公司。为什么提罗大佑加入任贤齐公司。因为罗大佑和小虫同是台湾四大音乐制作人。另外，小虫曾经被助理骗光所有钱财，且惹上官司时，任贤齐二话没说给他100万渡过难关。\r\n\r\n回过头来说任贤齐的音乐，从当初《心太软》的深情款款，到《春天花会开》的痞子青年，还有《任逍遥》的古典浪漫，最终化作如今絮絮叨叨唱着心情故事的新好男人。 \r\n\r\n单纯就歌唱而言，任贤齐的身上看不到太多陈升的风格，只是一直若隐若现的存在。\r\n\r\n《小雪》是陈升跟任贤齐二人合作的经典。 \r\n\r\n这首歌有一种很难形容的典型陈升式民谣风格，在当时如日中天的任贤齐身上产生了奇妙的化学效应，把当时唱了很多商业情歌的他身上的那股匠气瞬间清空。 \r\n\r\n陈升任贤齐亦师亦友。\r\n\r\n男人是大一点的孩子——《关于男人》\r\n\r\n男人都是大一点的孩子，所以他们喜欢和孩子一样的人一起玩。 物以类聚，陈升和他的朋友，比如萧言中，三小男人的张宇，都有着孩子气。\r\n\r\n看过《我是歌手2》，就能发现张宇和其他歌手的不同，他似乎一直就是在玩。 他在为儿子找儿媳妇，他为粉丝唱《舞娘》，他完成对陈志朋的承诺，他帮陈升对金城武唱《二十岁的眼泪》。（但愿20年后的金城武现在能听懂） 陈升一辈子在玩音乐，享受家人朋友的生活。\r\n\r\n他和萧言中用儿子的作业本画靶心，玩弹弹枪，第二天儿子发现作业本烂了，找到他爸爸，陈升像个孩子一样蜷缩成一团，怕面对儿子无辜的目光。 \r\n\r\n他能和朋友吃过午饭一起骑自行车7个小时，车轮变形，骑到荒山野岭天黑慌，晚上蹒跚着像企鹅一样彩排。 \r\n\r\n他演唱会上，边唱歌边喝酒，他为观众掏20万买酒，他对坐在台下的台北市长说，你今天带的酒不够，来台上，我们再喝一杯。\r\n\r\n他为了写歌，在黑龙江漠河摸爬滚打两个月，在云南一住就是一个季节，在厦门体验渔民和市井生活，撒网打鱼，和巷子里的人下象棋赌酒脱衣服。\r\n\r\n一颗不钉在机器上的螺丝 \r\n\r\n你羡慕他有萧言中、张宇、黄品源、萧煌奇、伍佰一样的朋友，他却不顾你的讨厌和左小祖咒搞在一起。你说他这几年的歌被左小祖咒带到沟里去了，他微博都懒得开。他说，关我屁事，关你屁事。 \r\n\r\n奶茶第一次开演唱会，她想请师傅去撑场，千辛万苦找到他。他说关我屁事，没我你就唱不了吗。奶茶苦苦哀求，他说你喝了这碗酒。刘若英端起海碗，咕咚咕咚喝完了。他说，我可能去，也可能不去。刘若英洒泪醉翻。 \r\n\r\n演唱会第四首歌是《为爱痴狂》，这是刘若英想与师傅在演唱会唱的歌，第三首歌接近尾声。奶茶回头看后台，依旧没有师傅的身影，鼓手也摇摇头。含泪和声唱，乃不见君来。 \r\n\r\n独自一人唱着《为爱痴狂》：“我从春天走来，你在秋天说要分开。说好不为你忧伤，但心情怎会无恙。”\r\n\r\n这时突然key突然降了一个调，她讶然忘记了唱歌，回头看去，他身着西装，衣服的标签还没摘。除了结婚时，这是他第二次穿西装。 \r\n\r\n唱歌的空隙，他说，我来是为了嫁女儿，不得不正式一点。 \r\n\r\n刘若英想要他一个拥抱，他迟疑，刘若英哽咽对观众说，大家帮我求求他。\r\n\r\n这还是对在意的人，对他人可想如何。 \r\n\r\n并不是他桀骜不驯，本来就不是流水线上的一颗螺丝钉。 \r\n\r\n写歌的人假正经，听歌的人最无情。"
            },
            "music_name": "把悲伤留给自己",
            "audio_author": "陈升"
        },
        {
            "id": "9089",
            "category": "4",
            "display_category": 6,
            "item_id": "1183",
            "title": "谢天谢地，他们当年没有选择做歌手",
            "forward": "“演了无数次别人，这次终于可以做一次自己。”",
            "img_url": "http://image.wufazhuce.com/Fn7dTKwakxn95jbKxIvCkbEz6KAB",
            "like_count": 124,
            "post_date": "2017-01-04 19:00:00",
            "last_update_date": "2017-01-03 22:49:32",
            "author": {
                "user_id": "0",
                "user_name": "GQ Lab",
                "web_url": "",
                "summary": "",
                "desc": "",
                "is_settled": "",
                "settled_type": "",
                "fans_total": "",
                "wb_name": ""
            },
            "video_url": "",
            "audio_url": "1771497667",
            "audio_platform": "1",
            "start_video": "",
            "volume": 0,
            "pic_info": "",
            "words_info": "",
            "subtitle": "I Dreamed A Dream",
            "number": 0,
            "serial_id": 0,
            "serial_list": [],
            "movie_story_id": 0,
            "ad_id": 0,
            "ad_type": 0,
            "ad_pvurl": "",
            "ad_linkurl": "",
            "ad_makettime": "",
            "ad_closetime": "",
            "ad_share_cnt": "",
            "ad_pvurl_vendor": "",
            "content_id": "1183",
            "content_type": "4",
            "content_bgcolor": "#FFFFFF",
            "share_url": "http://h.xiami.com/one-share.html?id=1771497667",
            "share_info": {
                "url": "http://h.xiami.com/one-share.html?id=1771497667",
                "image": "http://image.wufazhuce.com/Fn7dTKwakxn95jbKxIvCkbEz6KAB",
                "title": "「一个」音乐: GQ Lab I Dreamed A Dream",
                "content": "两年前，张曼玉第一次以摇滚歌手的身份亮相草莓音乐节时，唱歌完全“不着调”，以至于大批粉丝失望离场，“张曼玉一开口全场安静，有人形容这是被上帝放弃的声音。”据说最后，舞台还塌了。\r\n \r\n你当然可以欣赏她的勇气，赞美她的潇洒，并为她的真诚鼓掌。正如她所说：“演了无数次别人，这次终于可以做一次自己。”但如果你给你一道选择题：你更愿意看到她用心出演一部电影，还是更愿意听她倾情演绎一首歌曲？玩玩票无伤大雅，但难道咱们不应该感恩张曼玉没有在事业伊始就去追逐她最初的梦想吗？\r\n\r\n不止张曼玉，下面这些人对音乐有诸多各异的执着，但我们只能在心中齐声喊道：好险！还好他们当年没去唱歌。\r\n\r\n斯嘉丽·约翰逊\r\n因为和音乐制作人一起旅了一次游\r\n\r\n当寡姐斯嘉丽一袭性感小黑裙出现在“双十一”晚会上时，我们立马在心中高呼：“Oh, no, 千万别开口唱歌！” 不是想太多，只是因为我们真的听过寡姐之前的两张音乐作品。\r\n\r\n2008年，正当红的寡姐消失了一段时间，她声称自己和一位音乐制作人一起去旅行了，回来之后还打算把旅行的成果唱出来，于是，新专辑《Anywhere I Lay My Head》就这么面世了。\r\n\r\n这张专辑翻唱了 Tom Waits 的十首歌曲，你知道的，翻唱作品总是不太走运，这张唱片也不例外：“编曲很棒，唱歌的水平就......做鬼片配乐估计不错”、“听的时候请忘记她是斯嘉丽·约翰逊本人”、“声音与美貌不符”、“强烈建议下次出专辑附送人型抱枕”……\r\n \r\n但斯嘉丽对自己的表现也不怎么满意：“我希望 Tom Waits 的粉丝听完我的演唱后，不要把我围堵在酒吧里群殴我，更不要追着打我。”\r\n\r\n但是后来她还是执着地推出了（更没什么水花）的第二张专辑。\r\n\r\n小罗伯特·唐尼\r\n写歌就好比写日记\r\n\r\n你一定会以为“钢铁侠”嘛，唱的一定就是重金属或者摇滚之类的曲风，但其实私底下，这位超级英雄反而喜欢浅浅吟唱那些略显老气的爵士，甚至还带了些乡村和福音的气息。\r\n \r\n2004年底，小罗伯特·唐尼发布了个人音乐专辑《The Futurist》。整张专辑在“钢铁侠”饱含磁性和深情的声音中徐徐展开，饱满而内敛，沧桑而纯粹。\r\n \r\n总的来说，小罗伯特·唐尼对这张专辑还是挺满意的：“我觉得自己是一个很敏感的人，爱自省，对世界充满好奇，所以这张专辑里的每一首歌都是我的经历。”\r\n \r\n李冰冰\r\n用音乐呈现一个真冰冰\r\n\r\n“我会老老实实做人，认认真真唱歌。”李冰冰在2008年7月正式推出首张个人专辑《自&己》的时候，说自己进军乐坛绝对不是玩票，“在录制每一首歌时，都用尽了全身的力气，一口气吃上三碗饭才能补充回体力。”\r\n \r\n专辑名称“自己”背后包含了三层含义：“做.自己”、“很.自己”和“爱.自己”，几乎诠释了全部形态的李冰冰。\r\n \r\n这张专辑收录了一首由林俊杰制作的《一生的爱》，旋律清新柔美，但听众似乎并不买账。有评论说道，“这首歌真的被演绎出了沧桑的味道！不愧是一名演技派演员。”\r\n\r\n吴秀波\r\n专辑出来的时候已经胖到不想当歌手了\r\n\r\n吴秀波曾经自掏腰包，给自己制作了张专辑，名为《爱之战》，结果卖了11万的版权费，“当时崔健的专辑才卖12万！”对此，吴秀波颇为满意。\r\n \r\n不过当时的吴秀波其实并不识谱，据说，这张专辑里的词和曲都先被他记在脑子里，然后哼进录音机的。1996年录制的一张专辑因为一些原因，直到2000年才发行，但也并没有什么反响。\r\n \r\n“而且人到30岁，开始发胖了，突然间就认识到，我老了。那一次是我到现在为止认识到老感受最深的一次。这以后，我给自己的一个信息和决定就是：别再唱歌了。”\r\n\r\n陈建斌\r\n太太可以免费出演 MV ？\r\n\r\n2012年陈建斌在电影《人山人海》拍摄中，创作了自己的第一首单曲《契科夫来到我身边》，之后又一口气创作了10首新歌，包括一首写给蒋勤勤的，然后萌生了自费出专辑的念头，并且打算拉上太太蒋勤勤出演 MV。\r\n\r\n对于陈建斌的这首单曲，导演高希希愤然说道：“我们在片场都听过他唱歌，让我们‘震撼’，不出专辑简直天理难容！”而他的大学同学李亚鹏则有不同的看法：“我们在大学的时候，他就非常爱唱歌的，但是他绝对到不了能出专辑的水平，他唱谁的歌都是一样一样的的味道。”\r\n\r\n郝蕾\r\n最奇怪的脑回路：唱歌是为了让大家知道我会写词\r\n\r\n郝蕾在主演的话剧《恋爱中的犀牛》中第一次唱了主题曲《氧气》，当时外界的评论高度统一——惊艳。很多人以为她会趁势推出下一张专辑，没想到一隔就是7年。\r\n\r\n“歌手这个职业，其实对我来说蛮陌生的。我唱歌，只是想把我的词推荐给大家，但是如果我自己不唱的话，别人又不知道我会写词。所以那好吧，就自己先唱，就跟王婆卖瓜是一样的。也许就可能会有人（听到我唱歌）来找我写词，我主要目的是这样。”\r\n\r\n科比·布莱恩特\r\n为了激励自己，让自己（打球）能发挥到最好\r\n\r\n科比曾在2000年制作了一张说唱唱片，并且在当年的全明星赛上，与名模泰拉·班克斯合唱了主打歌《K.O.B.E》。万万没想到，这张唱片并没有引起任何反响。（看走眼的）索尼公司抢先签下科比之后，又不得不提前终止了合作。\r\n \r\n所以在科比唱歌这件事上，同是 NBA 运动员的“小飞侠”斯蒂芬·杰克逊可能说得对：“科比的说唱实在太糟糕了，他能出唱片完全靠的是名气。”\r\n\r\n科比表示，自己做音乐的目的“主要是激励自己，让自己能发挥到最好”。对于写歌的过程，他自认为很轻松：“我认为，写歌就像打篮球，熟能生巧。我现在写歌只需进入录音间，听听乐队演奏的曲子，然后歌词一挥而就，通常大约只用15分钟。”然后我们就知道这首专辑为什么没有大卖了。\r\n\r\n安妮·海瑟薇\r\n唱 Rapper 的才能似乎是天生的？\r\n\r\n安妮·海瑟薇的性感大嘴巴其实大有前途，前有上 Conan 秀大秀饶舌讽刺狗仔，后有与詹姆斯·戈登在新节目 Drop Themic 来了一段爆炸全场的 rap battle，而她在《悲惨世界》中所唱的《I dreamed a dream》也被入选为江苏省音乐高考曲目401首之一。\r\n\r\n汤姆·克鲁斯\r\n没办法，一开口就在喜马拉雅之巅\r\n\r\n歌手汤姆·克鲁斯其实早在日本就出道了——他曾趁着音乐电影《摇滚年代》上映之时，借机跑去日本发行了自己的专辑。《摇滚年代》共收录了20首歌曲，其中八首歌曲由汤姆·克鲁斯演唱。\r\n\r\n唱片制作人 Anders 第一次在汤姆·克鲁斯家里听到他唱歌的时候惊呼，“天啊，他的声带是如此的惊人，开口的瞬间，声波都要把我震飞了！这简直是我听到的史上最强音浪，那么响，还能去到任何想要的高度，就像一个小毛孩发现了新玩具，然后发出的超强分贝。”\r\n\r\n约翰尼·德普\r\n朋友出专辑，我就插一脚\r\n\r\n约翰尼·德普想成为摇滚歌星的事儿已经是老生常谈了，作为摇滚圈的“老炮儿”，他组过十几支乐队，但没有一支走到了最后，包括最出名的 Hollywood Vampires（好莱坞吸血鬼），除了乐队发行的专辑外，他还与奥斯卡影帝西恩·潘合作了一张唱片《强尼·戴普的左岸小酒馆》，收录了他认为好听的酒吧背景音乐。\r\n\r\n实际上，约翰尼·德普非常看不起那些利用名声进行音乐商业活动的电影明星，他在采访中称，演员做音乐的事让他感到非常恶心（？）。所以，他宁愿出现在好友的专辑中。 \r\n\r\n侯孝贤\r\n找人唱主题曲是要花钱的\r\n\r\n虽说唱歌只是侯孝贤的业余爱好，但如果不当导演，侯孝贤曾经的梦想真的是成为一名歌星。1986年他出版了唯一一张台语演唱专辑《太阳》，惊艳了业界，制作人蔡振南评价说：“声音的质感朴实，他像在亦肆亦语自己的人生。”按捺不住唱歌的热情，后来他又在《少年也，安啦》演唱了一首《梦中人》；在《戏梦人生》唱了《港边惜别》，在《好男好女》中和伊能静一起唱山歌。借自己的电影宣传自己的歌，如此“心机”也只有侯导了。\r\n \r\n“我唱歌很投入的，唱歌就好好唱嘛。写剧本写到很高兴的时候，都会不自觉地唱起歌，唱我自己都不知道的曲子。” 看，他的歌就像他的电影一样，一个人没有同类。\r\n\r\n北野武\r\n有着童心的老男孩\r\n\r\n没想到，这位北野武大叔也发行过自己的唱片。和他暴力美学的影视作品不同，音乐里的北野武总是煽情且温柔。一首 《City Bird》 可算他的口碑之作，像是唱着自己——一个不折不扣的老男孩。很难想象一个看起来极凶粗犷的日本大汉还有如此欢快孩子气的一面。最重要的是，“唱功好像比侯孝贤好？”\r\n\r\n但是，话又说回来，现在是个歌手都去拍电影拍电视剧拍网剧参加综艺节目玩直播代言网游开淘宝店去了，如今做歌手又没名又没钱（和当演员比），像张曼玉这样能给咱们惊喜的“新人”反倒是显得初心可贵了。"
            },
            "music_name": "I Dreamed A Dream",
            "audio_author": "安妮·海瑟薇"
        },
        {
            "id": "9130",
            "category": "4",
            "display_category": 6,
            "item_id": "1202",
            "title": "一路的少年，林宥嘉",
            "forward": "#那些一开口就不一样的男声#迷幻王子林宥嘉",
            "img_url": "http://image.wufazhuce.com/FoTPEx_I8MeGYAkk8stXSOXbLhEg",
            "like_count": 444,
            "post_date": "2017-01-04 17:00:00",
            "last_update_date": "2017-01-03 23:06:48",
            "author": {
                "user_id": "7642035",
                "user_name": "编号223",
                "desc": "城市美学私享者，以摄影、旅行、写作和自出版作为生活创作四件套，长期对焦新生代次文化和生活状态，探求当代中国新青年的爱与性及性别。微博：@编号223",
                "wb_name": "",
                "is_settled": "0",
                "settled_type": "0",
                "summary": "摄影艺术家、作家。",
                "fans_total": "38",
                "web_url": "http://image.wufazhuce.com/FpAKgW-9xE5NHGwmyJmKP1jfzixr"
            },
            "video_url": "",
            "audio_url": "1771093946",
            "audio_platform": "1",
            "start_video": "",
            "volume": 0,
            "pic_info": "",
            "words_info": "",
            "subtitle": "傻子",
            "number": 0,
            "serial_id": 0,
            "serial_list": [],
            "movie_story_id": 0,
            "ad_id": 0,
            "ad_type": 0,
            "ad_pvurl": "",
            "ad_linkurl": "",
            "ad_makettime": "",
            "ad_closetime": "",
            "ad_share_cnt": "",
            "ad_pvurl_vendor": "",
            "content_id": "1202",
            "content_type": "4",
            "content_bgcolor": "#FFFFFF",
            "share_url": "http://h.xiami.com/one-share.html?id=1771093946",
            "share_info": {
                "url": "http://h.xiami.com/one-share.html?id=1771093946",
                "image": "http://image.wufazhuce.com/FoTPEx_I8MeGYAkk8stXSOXbLhEg",
                "title": "「一个」音乐: 编号223 傻子",
                "content": "2011年6月，我在微博上发出了一张“胶片放荡”系列的照片，少年林宥嘉躺在房车的睡床上，半躺在睡床边角，紧靠着车窗，外面有风，扬起白色窗帘一角，似千百头麋鹿奔过，在狭小的房车空间，带起有诗意一般空气的流动，软软的，涩涩的，窗帘那一角形成弧线挡住少年的半张脸，眼是闭住的，身体是无力的，头发贴着额头，手指也有睡着的意味。就是这样的一张午后风马少年的照片里，这个人的嘴角却说着独有的跋扈且坚定的语言。\r\n\r\n我给这张照片起名叫“一路的少年”。\r\n\r\n时隔五年多，再来回忆那时事情，有些记忆毕竟都有淡化，或者丢失，能深刻记得见第一面，北京的春末，拍摄专辑《美妙生活》的家里屋内，一大早说了一声hi林宥嘉，我是摄影师223。\r\n\r\n拍摄是有来由的，聂永真，台湾最有才的平面设计师，我们曾合作过舞台剧宣传拍摄，那时见过两次，彼此互懂，用作品交流和说话。一日，永真说，“223你有没有兴趣拍林宥嘉的新唱片，我觉得这张唱片很适合找你拍。”我当然说好啊，一来唱片拍摄我是感兴趣的，二来能再次跟意思有想法的人合作，必定是合拍的。\r\n\r\n接下来回几次的邮件，关于拍摄的构思和概念，美妙生活在我脑子里已经形成它原有的雏形：（我的）空间里的宇宙观、（跟常人不同的）新方向感、生活变形与反方法。通常逆向思维的反叛手法本就是我那杯茶，“沉溺的个人行为语言、世界的反面是我、我正在生活”这些唱片组成的概念正中我下怀。\r\n\r\n我说，来来来，我找个旧房车，会更接近所谓“美妙生活”，再来一些旧皮箱、植物、单车、衣物、日常杂物，在郊外公路上找一种都市文明与自然野生的乌托邦自由感。\r\n\r\n于是拍摄定在室内和郊外两个场景。\r\n\r\n第一次见面，难免陌生，宥嘉拍摄团队的化妆师叫“小美人”，男生，对，男生叫小美人，我们一见如故，放肆开一些下作俗气的玩笑。我给宥嘉送了一本我的摄影集，他在翻阅期间，我讲了一个“相机”的笑话：“一女子坐出租车，把相机落在车上了，下车后司机在后面追着叫，小姐你相机你相机，女子回头狠狠地骂回了一句，你才相机。”\r\n \r\n所有人笑到披头散发。\r\n\r\n化解了初见的陌生感，接下来拍摄顺理成章变得相对轻松。自由的即兴发挥依旧行得通，从日常的带有戏谑感的场景开始：粉红桌布上切西柚，手指套黑橄榄的自我娱乐，胡乱裹在被子里留有窥视的眼睛，与柠檬嬉戏的耳朵和被面粉弄脏的手……都是一段段发生在日常又不寻常的情节。\r\n\r\n我们说拍照就像拍电影，每一个场次都有其独立的剧本。\r\n\r\n来到郊外，北京六环外人烟最少的公路，凌乱的日常杂物在租来的房车里外和公路旁边，发挥了反常理的符号化作用。\r\n\r\n要知道，北京的干燥空气，使得就算是郊外的公路，也都是灰尘滚滚，躺在公路边和草坪里，都不是体面和舒服的事，为了达到最好的意识反骨的效果，我说宥嘉你来躺下，躺在乱衣堆里，躺在干杂草上，他说好，“把自己当做流浪的吉普赛人，躺着是最不累的拍摄。”\r\n\r\n阳光是好的，那日，房车的车窗倒映出远处的山峦，这个把自己当做吉普赛人的少年，靠着窗坐在车内，温温吞吞地吃一块下午的饼干，山林树影打在有尘的玻璃上打在微微皱起的眉头。\r\n\r\n再见宥嘉是在台北小巨蛋“神游”演唱会的彩排现场，那时他的《美妙生活》专辑已经发布，粉丝们继续在他声音所营造的感官里钝痛并着迷。那个往日如邻家跑出房门的男孩，站在彩排的舞台灯光下，身体和声音就像离群的天马，发出光。\r\n \r\n这种感受在之后又一次的拍摄，“神游”北京站上再次领略，我被邀请做舞台现场摄影，他彩排时的内收在正式演出时全然迸发。我们没有改变什么，一如第一次见面，讲讲冷笑话，只是这一次看到的是站在绚烂灯光下面对万千歌迷的林宥嘉，一张口便切入你脑叶脏器的风光万丈的林宥嘉。那次照片，收录在了林宥嘉“神游”巡回演唱会DVD套书里。\r\n\r\n再后来，我写了一本书，《除非我们虚构了爱》，邀请宥嘉写一段推荐语，他写道：“因为223太会拍照了，于是我会私心地介意，他少拍一张照，也许下个世纪的少年便少了一个连结过去的可能 ；更何况他还花了时间精力额外写完了一本书。不过，我想他的确必须写。如果他不是一个对逝去的时间有所惦记的人，我们就不会总以为他照片里精疲力尽的对象，才刚在昨天对着镜头用力呼吸。”\r\n \r\n那个少年还是少年，我们各自走在声音和影像的长途中。我时时想起，那个北京3月的春末，一场拍摄耗掉我们一整天的时间，最后一个场景在黑夜里，少年于冷风中爬上房车顶，风吹得车晃得厉害，拿着烟火稳当当站立的他，在黑夜中，就像他如今的样子，跋扈如风，凛冽如光。"
            },
            "music_name": "傻子",
            "audio_author": "林宥嘉"
        },
        {
            "id": "9139",
            "category": "4",
            "display_category": 6,
            "item_id": "1194",
            "title": "我的语文老师罗大佑",
            "forward": "#那些一开口就不一样的男声#轻飘飘的旧时光就这么溜走。",
            "img_url": "http://image.wufazhuce.com/FvEeyhQt-hsIEPHFWs7DyLLuhn9-",
            "like_count": 274,
            "post_date": "2017-01-04 10:00:00",
            "last_update_date": "2017-01-03 23:35:28",
            "author": {
                "user_id": "7642198",
                "user_name": "张海坏",
                "desc": "编剧、专栏作家、自由撰稿人，小转盘附近比较英俊的知识分子。",
                "wb_name": "",
                "is_settled": "0",
                "settled_type": "0",
                "summary": "编剧、专栏作家、自由撰稿人",
                "fans_total": "15",
                "web_url": "http://image.wufazhuce.com/FjjJh6WLnpIo74s79bojMEYEfY29"
            },
            "video_url": "",
            "audio_url": "1770810451",
            "audio_platform": "1",
            "start_video": "",
            "volume": 0,
            "pic_info": "",
            "words_info": "",
            "subtitle": "光阴的故事",
            "number": 0,
            "serial_id": 0,
            "serial_list": [],
            "movie_story_id": 0,
            "ad_id": 0,
            "ad_type": 0,
            "ad_pvurl": "",
            "ad_linkurl": "",
            "ad_makettime": "",
            "ad_closetime": "",
            "ad_share_cnt": "",
            "ad_pvurl_vendor": "",
            "content_id": "1194",
            "content_type": "4",
            "content_bgcolor": "#FFFFFF",
            "share_url": "http://h.xiami.com/one-share.html?id=1770810451",
            "share_info": {
                "url": "http://h.xiami.com/one-share.html?id=1770810451",
                "image": "http://image.wufazhuce.com/FvEeyhQt-hsIEPHFWs7DyLLuhn9-",
                "title": "「一个」音乐: 张海坏 光阴的故事",
                "content": "我的语文老师罗大佑先生今年六十多岁了。\r\n\r\n读书的时候，有两个男人始终对我影响颇深，一个是鲁迅先生，一个就是罗大佑。因为我发现无论读到哪一年级，语文课里都会Random出一篇鲁大师的文章，而当鲁大师的文章只要一出现就免不了要承受熟读并背诵某个自然段的悲催。\r\n\r\n这时候罗大佑老师就像达克宁软膏一样，哪里不适爽哪里。每每待我背书背到头疼欲裂时就会在随身听里放一曲Tayu Lo，要说他俩的共同特征莫过于都曾弃医从文且骨子里嚣张跋扈，如果非要在二人的身上找一个破折号的话，可能就是罗大佑先生比鲁大师多会一手吉他，当然这对我来说绝逼是件好事儿。\r\n\r\n我能想象的到假如当年鲁大师要是也会一门乐器的话，今天的音乐课就不仅是听听歌这么简单的事儿了。\r\n\r\n池塘边的榕树上\r\n知了在声声叫着夏天\r\n\r\n歌曲《童年》最早的演唱者是张艾嘉女士，发行于1981年的滚石唱片公司。这是张艾嘉与罗大佑的第二次合作，也是罗大佑“弃医从文”后第一次以音乐制作人身份制作的第一张唱片。\r\n\r\n那时的张艾嘉早已成名多时，罗大佑心甘情愿地把《童年》送给了张艾嘉，除了她的名气之外，更重要的一个原因就是两人当时正上演着一场轰轰烈烈的爱情。虽然张艾嘉比罗大佑年长一岁，但罗大佑总是亲昵地称张艾嘉为“小妹”，并且后来还为张艾嘉创作了同称歌曲《小妹》，日后这个“小妹”也成为世人皆知的称呼。\r\n\r\n当然这些都是我听说来的史料，那一年我爸和我妈还不认识，我也还只是一滩水。但不可否认的是这首歌把我小学的回忆填得满满登登，每每儿童节演出中总有几个少年穿着小马甲，画着京剧般夸张的舞台装在操场上扮演如今看来和闰土差不多的形象。\r\n\r\n那时的福利社里面真的什么都有，口袋里也真是没有半毛钱；那时的操场的秋千上，还真的能看见蜻蜓停在上面。\r\n\r\n轻飘飘的旧时光就这么溜走\r\n转头回去看看时已匆匆数年\r\n\r\n从小学到初中，我整整奋斗了六年。《从百草园到三味书屋》，我整整背了一晚。\r\n\r\n这篇文章是鲁大师于1926年写的一篇童年妙趣生活的回忆性散文，收入《朝花夕拾》。文章采用白描手法充分展现了当时的VR技术，从百草园充满奇幻和梦境的天堂到守旧且陈腐的三味书屋，将虚拟与现实表达的淋漓尽致。\r\n\r\n那年我初二，因为家庭原因，不得以转校，遂从白雪皑皑的北国来到了万紫千红的江南。三月的第一次勃起，待我推进教室的木门，一眼就看到了坐在窗户边那个蓝外套女孩。后来我和她成了很好的朋友，好到整整一个学期的早饭她从没收过我一分钱，当然回报就是考试的时候我的语文试卷要给她抄。\r\n\r\n几乎每一次的考试，我的语文成绩都是班里最好的，尤其是作文。有次期中考试我心血来潮，把作文里的主角用了她的名字，后来我和她陆续被班主任叫到办公室，再后来，我也再没吃到过她的早餐。\r\n\r\n南方的雨季阴晴难测，轰隆隆的雷雨声在我的窗前，怎么也难忘记你离去的转变，孤单单的身影后寂寥的心情，永远无怨的应该是校门口的早餐店。\r\n\r\n\r\n我听到传来的谁的声音\r\n像那梦里呜咽中的小河\r\n\r\n从初中到高中我只用了读小学的一半时间，遗憾的是我把这一半的时间中的一多半用在了原本以为可以厮守终身的另一半的身上。是的，我恋爱了，正正八经的初恋。\r\n\r\n高中时期的语文课启动了令人发狂的模式，庆幸的是我的成绩还是一如既往的洒洒水莫蒙台。她本不该是我的女友，因为我的同桌爱她爱得死去活来，可惜这哥们文笔太烂胆子太小，于是和我达成“走肾条约”，他负责发自内心的口述，我帮他艺术加工成情书送给那个女孩，回报是帮我买早饭，一直买到他俩在一起为止。\r\n\r\n给女孩写情书，用鲁迅的风格不是不行，譬如我的心里有个人，一个是你，另一个也是你。不过我更欣赏罗大佑老师那种媚雅的情绪，于是，我白天背着《纪念刘和珍君》，晚上听着《你的样子》。把每一首情书都罗列成歌词的样式，一边哼着小曲一边创作情诗。\r\n\r\n我本想这段姻缘要是总处于模棱两可，那我就能天天吃到免费的早餐了，可惜好景不长，谁料那姑娘每次收到情书的时候都会露出无辜的眼神看我。一开始看看情书，看看我，再后来她看上了情书，也看上了我。\r\n\r\n任何的成功都是要付出代价的，我大概的确是恋爱了，代价就是挨了一顿揍丧失了免费的早餐，而且还要把每周一百块的生活费挤出来给她买早饭。\r\n\r\n后来她胖了，胖得一发不可收拾。我看到远去的谁的步伐，遮住告别时哀伤的眼神，不明白的是为何你情愿，让风尘刻画一个胖子。\r\n\r\n你不属于我 我也不拥有你\r\n姑娘世上没有人有占有的权利\r\n\r\n大学就像送给我失恋受伤后的创可贴，告诉我那里的世界比高中更加精彩。\r\n\r\n开往杭州的绿皮火车摩擦着锈迹斑斑的铁轨，我和老牛坐在靠窗的位置，我们对面的两个姑娘，头发一长一短，同样也是去往杭州求学。南方的九月还像夏天一样死皮赖脸的热，我想搭讪，老牛也是。我们俩悄悄嘀咕了半天，最后那俩女孩没忍住，主动问我们去哪。四个人的你来我往是从一副五块钱的扑克牌开始的，没赌钱，赌的是下车后谁送谁。\r\n\r\n碰巧我喜欢的女孩被老牛赢去了，而我只能愿赌服输地送这个小短发。两个人带着一副耳机挤在公交车里，她说她也喜欢听老歌。大学新书发下来我第一时间看了下语文，居然没有鲁大师的文章，我突然不知道该干些什么。\r\n\r\n再后来我们的见面也总是四个人集体式的沙龙，老牛和那个长发飘飘已经可以厚颜无耻地在我们面前秀恩爱了， 可他不知道，我喜欢的也是长发飘飘。大二我代表学校参加高校辩论赛，半决赛是在长发飘飘的学校举行，不出意料地赢了。\r\n\r\n结束后她带我去吃食堂，那天晚上我没回学校，长发飘飘也没回。今天的欢乐，将是明天创痛的回忆，什么都可以抛弃，什么也不能忘记。长发飘飘后来和老牛分手了，她没和我在一起，我和老牛也还是很好的兄弟。\r\n\r\n我发现毕业后，我曾背的那些鲁大师的作品并没能给我生活带来什么，倒是陪客户去KTV的时候常常会点几首罗大佑的乐呵乐呵。\r\n\r\n罗大佑的伟大，不在于他之乎者也的嬉笑怒骂，也不在于他对爱人同志的款款深情，而在于他身后的整整一代，甚至是尚未来世的一代。\r\n\r\n鲁大师的伟大，不在于他彷徨呐喊中的横眉冷对千夫指，也不在于他热风野草里的俯首甘为孺子牛。我没能和鲁大师独处一世，我了解他的只能从小学到高中的课本里，而后的认识，我全然依托在另一个人的身上。\r\n\r\n这些年，罗大佑的歌让我很茫然也很快乐，他能够唱出横跨三十载的恋曲，也能为京城初夏的千百亡灵呼号，他能把东方之珠的沧桑和踟躇写在笔下，能拾起一枚印着英国女王的硬币把玩，亦能一个人在西门町闲逛，看所谓文明在马路上横撞直冲，也能偶尔到水果店里看看苹果的价格闻一闻老板娘身上的味道。\r\n\r\n我想这就是生活，有些老师教会了你一加一等于二，有些老师教会你如何能吃到免费的早饭。"
            },
            "music_name": "光阴的故事",
            "audio_author": "罗大佑"
        },
        {
            "id": "9161",
            "category": "4",
            "display_category": 6,
            "item_id": "1067",
            "title": "五十岁，拍马过山丘",
            "forward": "面相诚恳带两分狡黠，曲意诙谐时有三分滑稽，这是他的本色。他是个情种。",
            "img_url": "http://image.wufazhuce.com/FqoJpDB6H9RLnWwsc0FqtP8AzVrh",
            "like_count": 904,
            "post_date": "2017-01-04 06:00:00",
            "last_update_date": "2017-01-04 13:31:44",
            "author": {
                "user_id": "7644681",
                "user_name": "李皖",
                "desc": "李皖，祖籍安徽，1966年生于江苏徐州，1985年考入复旦大学新闻系，曾任《武汉晨报》副总编辑。业余从事音乐评论写作，著有《回到歌唱》、《听者有心》、《民谣流域》、《摇滚1955―1999》等。",
                "wb_name": "",
                "is_settled": "0",
                "settled_type": "0",
                "summary": "知名乐评人",
                "fans_total": "17",
                "web_url": "http://image.wufazhuce.com/FuppxzQD8U1M2vNTtfdg4vhwaivR"
            },
            "video_url": "",
            "audio_url": "1772001102",
            "audio_platform": "1",
            "start_video": "http://music.wufazhuce.com/lgy6__UXqNn4dbvydOjwYZVIQRjQ",
            "volume": 0,
            "pic_info": "",
            "words_info": "",
            "subtitle": "山丘",
            "number": 0,
            "serial_id": 0,
            "serial_list": [],
            "movie_story_id": 0,
            "ad_id": 0,
            "ad_type": 0,
            "ad_pvurl": "",
            "ad_linkurl": "",
            "ad_makettime": "",
            "ad_closetime": "",
            "ad_share_cnt": "",
            "ad_pvurl_vendor": "",
            "content_id": "1067",
            "content_type": "4",
            "content_bgcolor": "#FFFFFF",
            "share_url": "http://h.xiami.com/one-share.html?id=1772001102",
            "share_info": {
                "url": "http://h.xiami.com/one-share.html?id=1772001102",
                "image": "http://image.wufazhuce.com/FqoJpDB6H9RLnWwsc0FqtP8AzVrh",
                "title": "「一个」音乐: 李皖 山丘",
                "content": "过了2008年，李宗盛已经50岁。50岁是个标志性的年龄，人生开始转暗，生理的、心理的暗示不期乃见。个人可以命硬，但社会、群体的定势如雾气沉沉，难以避开，即使个人力量可以强大到无视它，那份外在的压力却终究去不掉。\r\n\r\n2006年5月，李宗盛启动了《理性与感性作品音乐会》，到2009年初，演出最后一场，等于回顾总结自己的个人创作，在50岁上作一个收束。这份收束很沉，像是一棵巍巍大树，树上的果子已在历年淅淅落下，现在，用了一个咒语，果子们重回枝头，密集而饱满，累累沉沉，簇拥于同一个时辰，愈显出这大树的庞然与壮观。\r\n\r\n50岁后，李宗盛的词曲作品不再量产化，制作的事也少管，实际上进入了半退伍状态。他零零星星地写歌，盘桓在50岁的年龄上，又写出两首重量之作：一首是2010年《给自己的歌》，一首是2013年的《山丘》。两首歌都是自传性的，都是对自己生命的回顾，是发生在50岁这个年龄上的心境记录，值得认真听一听。\r\n\r\n在2011年华语传媒音乐奖的评审会上，《给自己的歌》获得了一致赞赏。赞赏不稀奇，稀奇的是，那是少有的一回，评委们感到自己被击中了，那些歌词和乐句，句句砸在了心坎。如果说这30多年来，李宗盛是华人心境的代言人，那么，《给自己的歌》，他又代言了一次，代言的主要是华人中的中年人。\r\n\r\n《山丘》有一个总结功名的开头。还是一生回首，李宗盛非常坦诚地，坦白了他这些年的创作心迹：写歌留给世人，这就是他这一生的梦想，让人唱，让人记着——说不定这些小情小爱小念，建成了一生的功业呢。现在，坐在50岁这个山头上感慨：可能还是没成熟，还是没活明白。但居然就已经五十了，快老了。“心里活着的，还是那个年轻人”。50岁是这样的感觉，有点奇怪，有点意外。\r\n\r\n更意外的还不是这，回顾这50年的人生，终究，悟明白了什么没有？\r\n\r\n回首50年的每一步，都像是翻山，不停地翻山。我们是不安的，所以频频回首。我们是贪心而无知的，所以拼命索求。我们是自尊而自强的，所以羞耻于求救、不知疲倦地翻越。现在，到了山的这一边了——\r\n\r\n想不朽，不朽还没有影，但人已经把自己弄丢了，头发已经花白了，时间在哗哗哗地流。山丘之后，无人等候，仍然是孤独的自己，仍然是什么也不明白。年少的时候，以为翻过山去，就能见识到山那边的世界，就能见到人生的答案，但山的这一边，也没有答案。\r\n\r\n这首歌有一个奇怪的线路。“越过山丘 才发现无人等候/喋喋不休 再也唤不回温柔”——“温柔”，从这个词，功名突然转向了女人。“为何记不得上一次是谁给的拥抱/在什么时候”，紧接着的这一句，立意完全落位在女人了，功名已经没影。而再往下走，再起一段，女人的话题又转向，爱情转向了友情。\r\n\r\n这里有李宗盛所娴熟的商业智慧。歌唱到了这里，是副歌的结句，在歌曲中，这是很重要的一句。定位于爱情，比例瞬间得到了调换，回到了情歌，甚至使前面的关于建功立业的感慨，也有了几分有关情爱的意义。流行歌曲中，情歌才是最大的，这样的处理，可以挠爱情的痒，找到更多的听众。\r\n\r\n往坏处看，这是惯性，是习性，让这回顾反省的翻越，搁浅在了河沟。从本性来说，李宗盛也确实是个情种，半生都在情事中费心，习染而成习惯。\r\n\r\n“我没有刻意隐藏 也无意让你感伤”，第一次听这歌的时候，很难有不听岔的——顺接着上句副歌的意思，会误以为这是对情侣的表白——再往下，才明白了，敢情这是对老友的絮叨；而整首歌的乐境，包括第一段中出现的“我俩”，至此也一下子明朗起来。\r\n\r\n鉴于李宗盛写过《和自己赛跑的人》，可以假定，说话对面的这个人，就是张培仁——李宗盛从发小、到考不上大学的难友、到一起去唱片业打拼的同事，再到这50多岁，感情维系一直不变的老友。\r\n\r\n《山丘》就是在酒桌上，或者，在茶室，在咖啡馆，或者就在家中，一壶茶，一杯酒，与像张培仁这样的老友晤谈。一起回顾从前的人与事，一同感念这人生的际遇悲喜。“多少次我们无醉不欢/咒骂人生太短 唏嘘相见恨晚/让女人把妆哭花了也不管”，唱到了这儿，这歌又成了友情的赞歌了。这份友情的厚重，真令人羡慕，配之以汉子式的酣唱，是人生的十足慰藉。\r\n\r\n“遗憾我们从未成熟/还没能晓得 就已经老了/尽力却仍不明白/身边的年轻人”，这都是写实。50年的人生，终究，没弄明白什么。在唱片业，关注年轻人，探究青少年心理，把握潮流的方向，是最基本的一个工作。曾经这活儿玩得得心应手，现在，也弄不明白了。时代大潮就这么轻轻地把50岁的老家伙推到了一边。\r\n\r\n《山丘》和《给自己的歌》是两块大石，压在50岁的胸口，也压在李宗盛的箱底。它们是可以压箱底的。李宗盛的口白式唱腔，到了这个年龄才真正是老道了，真气勃发气韵饱满吐词肯定，每一句都有不容置疑的肯定，充满艺术说服力的肯定。而他的说唱式作曲，更到了炉火纯青的火候，有了法无定法、规无常规、随兴而发、随意而为的自然天成。“她的爱在心里 埋藏了 抹平了 几年了/仍有余威”这段，插在主副歌之间，从歌词形式和长度看，从这个位置要达到的情绪看，实实在在是个难点，李宗盛却用仿若京剧的手法，每个字都处理成重音，把这一段处理成了中年心悸的一记记重锤，使峰线上又现一峰。\r\n\r\n《山丘》的作曲，进入了化境。全篇依字行腔，每一个字都音腔相合，落口准狠；需要感情变化的时候，转腔和旋律动作小但落位深。一开篇钢琴的萧飒深寒，途中转往吉他的娓娓弹奏，后半部交响乐的苍苍煌煌，都落在感情的刃口上，非常动人，也非常准确。尤其是最后一段，副歌中的句子颠倒了顺序，将“向情爱的挑逗 命运的左右/不自量力地还手 直至死方休”放在了段尾，最后再接“为何记不得上一次是谁给的拥抱/在什么时候”作为尾声，彻底把这首歌的色调，从悲情的感叹改向了不向命运低头的奋争。像西西弗斯无怨无悔地把滚下的石头一次次再推向山顶，这种看清后的转念，彻底改变了荒谬人生的处境和意义。\r\n\r\n要说，每个人都有他人格的命定。李宗盛这个人，面相诚恳带两分狡黠，曲意诙谐时有三分滑稽，这是他的本色。他是个情种。只有这样的情种，才分外讨人欢喜。当他用情极深时，那情意的缠绵之中，往往又有一种敞亮的东西，闪出光泽，并非一味让人深陷。在情爱中，虽然他不是智者，但聪明总现着几分，最终不失梦醒的判断与跳脱。尤其是他自己的歌，他的那种唱法，更显达观。说到底，这可能是些小情小调，词义婉约，甚至有时让人崩溃，但他唱出来，从来有一种开朗豪放，正气大方。\r\n\r\n比如《山丘》，它显示的可不是认命，虽然时有沉郁，却是50岁上仍不服输、仍奋力向前的形象。那些人生感慨，对时光逝去的痛惜，到最后全变成了无悔，变成了经历过一切的自豪。直至最后，向后看的晚宴变成了向前看的启程。在交响乐、钢琴、吉他的辉煌合奏中，歌手的声音愈加响亮，仿佛在胜利的进行曲中，将一生的真气鼓荡着，向着前面更多的一座座山丘，拍马豪迈越过。\r\n\r\n作者介绍：\r\n李皖，知名乐评人。"
            },
            "music_name": "山丘",
            "audio_author": "李宗盛"
        }
    ]
}